mahos/__init__.py
mahos/cli/__init__.py
mahos/cli/data.py
mahos/cli/data_ls.py
mahos/cli/data_print.py
mahos/cli/echo.py
mahos/cli/graph.py
mahos/cli/launch.py
mahos/cli/log.py
mahos/cli/ls.py
mahos/cli/main.py
mahos/cli/plot.py
mahos/cli/run.py
mahos/cli/shell.py
mahos/cli/threaded_nodes.py
mahos/cli/util.py
mahos/gui/Qt.py
mahos/gui/__init__.py
mahos/gui/basic_meas.py
mahos/gui/camera.py
mahos/gui/camera_client.py
mahos/gui/client.py
mahos/gui/common_widget.py
mahos/gui/confocal.py
mahos/gui/confocal_client.py
mahos/gui/dialog.py
mahos/gui/digital_out.py
mahos/gui/fit_widget.py
mahos/gui/gui_node.py
mahos/gui/hbt.py
mahos/gui/hbt_client.py
mahos/gui/inst_client.py
mahos/gui/iodmr.py
mahos/gui/iodmr_client.py
mahos/gui/log_client.py
mahos/gui/main_monitor.py
mahos/gui/main_monitor_widget.py
mahos/gui/manager_client.py
mahos/gui/odmr.py
mahos/gui/odmr_client.py
mahos/gui/oe200.py
mahos/gui/param.py
mahos/gui/param_client.py
mahos/gui/podmr.py
mahos/gui/podmr_client.py
mahos/gui/pulse_monitor.py
mahos/gui/pulse_monitor_client.py
mahos/gui/spectroscopy.py
mahos/gui/spectroscopy_client.py
mahos/gui/breeze_resources/__init__.py
mahos/gui/breeze_resources/dark/__init__.py
mahos/gui/breeze_resources/dark/ads_close.svg
mahos/gui/breeze_resources/dark/ads_close_hover.svg
mahos/gui/breeze_resources/dark/ads_close_pressed.svg
mahos/gui/breeze_resources/dark/ads_detach.svg
mahos/gui/breeze_resources/dark/ads_detach_hover.svg
mahos/gui/breeze_resources/dark/ads_detach_hover_pressed.svg
mahos/gui/breeze_resources/dark/ads_maximize.svg
mahos/gui/breeze_resources/dark/ads_maximize_hover.svg
mahos/gui/breeze_resources/dark/ads_maximize_pressed.svg
mahos/gui/breeze_resources/dark/ads_menu_button.svg
mahos/gui/breeze_resources/dark/ads_menu_button_hover.svg
mahos/gui/breeze_resources/dark/ads_menu_button_pressed.svg
mahos/gui/breeze_resources/dark/branch_closed.svg
mahos/gui/breeze_resources/dark/branch_closed_hover.svg
mahos/gui/breeze_resources/dark/branch_end.svg
mahos-0.2.2.dist-info/LICENSE
mahos-0.2.2.dist-info/METADATA
mahos-0.2.2.dist-info/WHEEL
mahos-0.2.2.dist-info/entry_points.txt
mahos-0.2.2.dist-info/top_level.txt
mahos-0.2.2.dist-info/RECORD
