Metadata-Version: 2.1
Name: mahos
Version: 0.2.2
Summary: Measurement Automation Handling and Orchestration System
Author-email: Kosuke Tahara <ktaha@mosk.tytlabs.co.jp>
License: BSD License (BSD-3-Clause)
Project-URL: Homepage, https://github.com/ToyotaCRDL/mahos
Project-URL: Documentation, https://toyotacrdl.github.io/mahos
Project-URL: Repository, https://github.com/ToyotaCRDL/mahos.git
Project-URL: Changelog, https://github.com/ToyotaCRDL/mahos/blob/main/CHANGELOG.rst
Keywords: measurement automation,laboratory automation,instrumentation
Classifier: Programming Language :: Python :: 3
Requires-Python: <3.11,>=3.8
License-File: LICENSE
